{
  "Title": "Just Friends",
  "Composer": "Klenner John",
  "Key": "G",
  "Rhythm": "Medium Swing",
  "Sections": [
    {
      "Label": "A",
      "MainSegment": {
        "Chords": "C^7|C^7|C-7|F7|G^7|G^7|Bb-7|Eb7"
      },
      "Endings": []
    },
    {
      "Label": "B",
      "MainSegment": {
        "Chords": "A-7|D7|G^7|E-7|A7|A7|A-7,D7|D-7,G7"
      },
      "Endings": []
    },
    {
      "Label": "A",
      "MainSegment": {
        "Chords": "C^7|C^7|C-7|F7|G^7|G^7|Bb-7|Eb7"
      },
      "Endings": []
    },
    {
      "Label": "C",
      "MainSegment": {
        "Chords": "A-7|D7|F#h7,B7b9|E-7|A7|A-7,D7|G6|D-7,G7"
      },
      "Endings": []
    }
  ]
}