{
  "Title": "Moment's Notice",
  "Composer": "John Coltrane",
  "Key": "Eb",
  "Rhythm": "Up Tempo Swing",
  "TimeSignature": "4/4",
  "Sections": [
    {
      "MainSegment": {
        "Chords": "Em7,A7|Fm7,Bb7|Ebmaj7|Abm7,Db7|Dm7,G7|Ebm7,Ab7|Dbmaj7|Dm7,G7|Cm7,B7|Bbm7,Eb7|Abmaj7|Abm7,Db7"
      },
      "Endings": [
        {
          "Chords": "Gm7,C7|Abm7,Db7|Gb6|Fm7,Bb7"
        },
        {
          "Chords": "Gm7,C7|Fm7,Bb7|Eb6/Bb|Fm7/Bb|Gm7/Bb|Fm7/Bb|Eb6/Bb,Fm7/Bb|Gm7/Bb,Fm7/Bb|Eb6,|"
        }
      ]
    }
  ]
}