{
  "Title": "This Year's Kisses",
  "Composer": "Berlin Irving",
  "Key": "G",
  "Rhythm": "Medium Swing",
  "Sections": [
    {
      "Label": "A",
      "MainSegment": {
        "Chords": "G^7|G^7,G^7,G#o7|A-7,D7|A-7,D7"
      },
      "Endings": [
        {
          "Chords": "G^7,G#o7|A-7,D7"
        },
        {
          "Chords": "G^7|D-7,G7"
        }
      ]
    },
    {
      "Label": "B",
      "MainSegment": {
        "Chords": "C^7|C^7|C-7|C-7|G^7|A7|A-7|D7"
      },
      "Endings": []
    },
    {
      "Label": "C",
      "MainSegment": {
        "Chords": "G^7|G^7,G^7,G#o7|A-7,D7|A-7,D7|B-7,E7|A-7,D7|G6,Bbo7|A-7,D7"
      },
      "Endings": []
    }
  ]
}